{
  "biblio_authors": "Harvard Business Review",
  "biblio_location": "相1F一般300",
  "biblio_publisher": "ダイヤモンド社",
  "biblio_year_published": "2002.2",
  "description": "ビジネスのあらゆる場面に交渉はつきものだ。組織外はもちろんのこと、組織内の意思決定でも交渉は行われる。組織内の対立や企業間の紛争などを解決するのにも、交渉力がものをいう。つまり交渉術とは、戦略を立案・実行するマネジャーにとって、欠かせないスキルである。だが交渉力は、ともすれば個人の能力に帰されがちだ。それを思考技術としてとらえ、さまざまな観点から論じたのが本書である。",
  "identifier": "4478770123",
  "keywords": [],
  "lexemes": [
    "ビジネス",
    "あらゆる",
    "場面",
    "交渉",
    "つきもの",
    "だ",
    "組織",
    "外",
    "もちろん",
    "こと",
    "組織",
    "内",
    "意思",
    "決定",
    "交渉",
    "行わ",
    "れる",
    "組織",
    "内",
    "対立",
    "企業",
    "間",
    "紛争",
    "解決",
    "する",
    "の",
    "交渉",
    "力",
    "もの",
    "いう",
    "つまり",
    "交渉",
    "術",
    "戦略",
    "立案",
    "実行",
    "する",
    "マネジャー",
    "欠か",
    "せ",
    "ない",
    "スキル",
    "で",
    "ある",
    "だ",
    "交渉",
    "力",
    "ともすれば",
    "個人",
    "能力",
    "帰さ",
    "れ",
    "がち",
    "だ",
    "それ",
    "思考",
    "技術",
    "とらえ",
    "さまざま",
    "な",
    "観点",
    "論じ",
    "た",
    "の",
    "本書",
    "で",
    "ある"
  ],
  "title": "交渉の戦略スキル"
}