{
  "biblio_authors": "苅谷 剛彦",
  "biblio_location": "相1F一般300",
  "biblio_publisher": "玉川大学出版部",
  "biblio_year_published": "1998.11",
  "description": "本書の1章と2章では、今日の大学大衆化のもとで、入学者選抜がどのような問題を抱えているのかを検討している。つぎの3章では、近年の高校教育改革に注目して、それが大学教育にどのような影響を及ぼしうるのかを考察した。続く4章では、そのようにして入学してくる新入生を大学がいかに受け入れるかについて、教育改革との関連で検討している。5章では、近年のカリキュラム改革の動向をまとめるとともに、ケーススタディとして京都大学、東京大学の二つを取り上げ、総合大学における「教養(部)」教育改革について検討した。つづく6章では、大学改革における教育の「質」の問題について考察した。7章では、大学における教育改善を支援するシステムについて、とりわけアメリカの事例をもとに検討し、8章では、大学院での教育・研究指導についての論考を納めた。そして、終章では、日本の大学がどこに向かおうとしているのか、日本の大学の「迷走」についての考察をのせた。",
  "identifier": "4472301016",
  "keywords": [],
  "lexemes": [
    "本書",
    "1",
    "章",
    "2",
    "章",
    "で",
    "今日",
    "大学",
    "大衆",
    "化",
    "もと",
    "で",
    "入学",
    "者",
    "選抜",
    "どの",
    "よう",
    "な",
    "問題",
    "抱え",
    "いる",
    "の",
    "検討",
    "し",
    "いる",
    "つぎ",
    "3",
    "章",
    "で",
    "近年",
    "高校",
    "教育",
    "改革",
    "注目",
    "し",
    "それ",
    "大学",
    "教育",
    "どの",
    "よう",
    "な",
    "影響",
    "及ぼし",
    "うる",
    "の",
    "考察",
    "し",
    "た",
    "続く",
    "4",
    "章",
    "で",
    "その",
    "よう",
    "し",
    "入学",
    "し",
    "くる",
    "新入生",
    "大学",
    "いかに",
    "受け入れる",
    "教育",
    "改革",
    "関連",
    "検討",
    "し",
    "いる",
    "5",
    "章",
    "で",
    "近年",
    "カリキュラム",
    "改革",
    "動向",
    "まとめる",
    "ケース",
    "スタディ",
    "京都大学",
    "東京大学",
    "二つ",
    "取り上げ",
    "総合大学",
    "教養",
    "部",
    "教育",
    "改革",
    "検討",
    "し",
    "た",
    "つづく",
    "6",
    "章",
    "で",
    "大学",
    "改革",
    "教育",
    "質",
    "問題",
    "考察",
    "し",
    "た",
    "7",
    "章",
    "で",
    "大学",
    "教育",
    "改善",
    "支援",
    "する",
    "システム",
    "とりわけ",
    "アメリカ",
    "事例",
    "もと",
    "検討",
    "し",
    "8",
    "章",
    "で",
    "大学院",
    "教育",
    "研究",
    "指導",
    "論考",
    "納め",
    "た",
    "そして",
    "終章",
    "日本",
    "大学",
    "どこ",
    "向かお",
    "う",
    "し",
    "いる",
    "の",
    "日本",
    "大学",
    "迷走",
    "考察",
    "のせ",
    "た"
  ],
  "title": "変わるニッポンの大学"
}