{
  "biblio_authors": "西野 武彦",
  "biblio_location": "相1F一般300",
  "biblio_publisher": "PHP研究所",
  "biblio_year_published": "2006.5",
  "description": "株式投資に欠かせない、情報戦略の王道!いかに情報武装するかが、あなたの投資の明暗を分ける。日常の新聞の読み方から、株価変動要因となった最近のケーススタディまで、基本中の基本を詳細に解説。",
  "identifier": "4569649882",
  "keywords": [],
  "lexemes": [
    "株式",
    "投資",
    "欠か",
    "せ",
    "ない",
    "情報",
    "戦略",
    "王道",
    "いかに",
    "情報",
    "武装",
    "する",
    "あなた",
    "投資",
    "明暗",
    "分ける",
    "日常",
    "新聞",
    "読み方",
    "株価",
    "変動",
    "要因",
    "なっ",
    "た",
    "最近",
    "ケース",
    "スタディ",
    "基本",
    "中",
    "基本",
    "詳細",
    "解説"
  ],
  "title": "株に強くなる「経済ニュース」のスルドイ読み方"
}