{
  "biblio_authors": "時事通信社",
  "biblio_location": "相1F一般300",
  "biblio_publisher": "時事通信社",
  "biblio_year_published": "2000.5",
  "description": "時代の最先端を行く若手から、既存業界の雄とされるベテランまで、ビジネスリーダー34人の姿を通して「日本経済」の近未来を読む。",
  "identifier": "4788700611",
  "keywords": [],
  "lexemes": [
    "時代",
    "最先端",
    "行く",
    "若手",
    "既存",
    "業界",
    "雄",
    "さ",
    "れる",
    "ベテラン",
    "ビジネス",
    "リーダー",
    "34",
    "人",
    "姿",
    "日本",
    "経済",
    "近",
    "未来",
    "読む"
  ],
  "title": "キーパーソン&キーワードで読む企業家たちの挑戦"
}