{
  "biblio_authors": "塩原 俊彦",
  "biblio_location": "相1F一般300",
  "biblio_publisher": "丸善",
  "biblio_year_published": "1998.10",
  "description": "混迷するロシアの政治・経済の本質的な問題はどこにあるのか。現代企業の構造と政治家の実像、その関係に迫る。",
  "identifier": "4621060759",
  "keywords": [],
  "lexemes": [
    "混迷",
    "する",
    "ロシア",
    "政治",
    "経済",
    "本質",
    "的",
    "な",
    "問題",
    "どこ",
    "ある",
    "の",
    "現代",
    "企業",
    "構造",
    "政治",
    "家",
    "実像",
    "その",
    "関係",
    "迫る"
  ],
  "title": "現代ロシアの政治・経済分析"
}