{
  "biblio_authors": "井手 正介",
  "biblio_location": "相1F一般300",
  "biblio_publisher": "日本経済新聞社",
  "biblio_year_published": "2005.7",
  "description": "グレアム=バフェット流の銘柄選択を日本株に応用した画期的テキスト!類書では得られぬ「実践力」が身につく。",
  "identifier": "4532132975",
  "keywords": [],
  "lexemes": [
    "グレアム",
    "バフェット",
    "流",
    "銘柄",
    "選択",
    "日本",
    "株",
    "応用",
    "し",
    "た",
    "画期的",
    "テキスト",
    "類書",
    "得",
    "られ",
    "ぬ",
    "実践",
    "力",
    "身",
    "つく"
  ],
  "title": "ビジネス・ゼミナール証券分析入門"
}