{
  "biblio_authors": "山下 範久",
  "biblio_location": "相1F一般300",
  "biblio_publisher": "講談社",
  "biblio_year_published": "2006.1",
  "description": "二一世紀、グローバル化する世界。“帝国”は脱領土化し、「言説空間」に闘争の場を移す。ネグリ/ハート『帝国』の問題提起を受け、「言説的権力としての帝国」によるヘゲモニー闘争として世界を読む画期的論考。",
  "identifier": "4062583518",
  "keywords": [],
  "lexemes": [
    "二",
    "一",
    "世紀",
    "グローバル",
    "化",
    "する",
    "世界",
    "帝国",
    "脱",
    "領土",
    "化",
    "し",
    "言説",
    "空間",
    "闘争",
    "場",
    "移す",
    "ネグリ",
    "ハート",
    "帝国",
    "問題",
    "提起",
    "受け",
    "言説",
    "的",
    "権力",
    "帝国",
    "ヘゲモニー",
    "闘争",
    "世界",
    "読む",
    "画期的",
    "論考"
  ],
  "title": "帝国論"
}