{
  "biblio_authors": "女性の職業研究会",
  "biblio_location": "相1F一般300",
  "biblio_publisher": "啓明書房",
  "biblio_year_published": "[2001.10]-",
  "description": "好きなこと、やりたいこと、興味のあることを自分の仕事に。女性の進出がめざましい職業の総合ガイド!女性に注目される職業230種をピックアップ。ジャンル別13分野に分けて掲載。仕事内容、資格の取り方、収入等をわかりやすく解説。就職までのルートマップをチャートで紹介。仕事名から検索できるインデックス付。",
  "identifier": "4767111021",
  "keywords": [],
  "lexemes": [
    "好き",
    "な",
    "こと",
    "やり",
    "たい",
    "こと",
    "興味",
    "ある",
    "こと",
    "自分",
    "仕事",
    "女性",
    "進出",
    "めざましい",
    "職業",
    "総合",
    "ガイド",
    "女性",
    "注目",
    "さ",
    "れる",
    "職業",
    "230",
    "種",
    "ピックアップ",
    "ジャンル",
    "別",
    "13",
    "分野",
    "分け",
    "掲載",
    "仕事",
    "内容",
    "資格",
    "取り",
    "方",
    "収入",
    "等",
    "わかり",
    "やすく",
    "解説",
    "就職",
    "ルート",
    "マップ",
    "チャート",
    "紹介",
    "仕事",
    "名",
    "検索",
    "できる",
    "インデックス",
    "付"
  ],
  "title": "女性の職業のすべて"
}