{
  "biblio_authors": "飯沼 博一",
  "biblio_location": "相1F一般300",
  "biblio_publisher": "白桃書房",
  "biblio_year_published": "2003.3",
  "description": "国際貿易理論の生成・発展,その理論の位置づけを,J. ステュアートからスミス,リカード,ミル,マーシャルやケインズ,シュムペーターの論理的視座における究明を試みつつ,東・東南アジアの問題点とその解決の道を探る力作。",
  "identifier": "4561761462",
  "keywords": [],
  "lexemes": [
    "国際",
    "貿易",
    "理論",
    "生成",
    "発展",
    "",
    "その",
    "理論",
    "位置づけ",
    "",
    "J",
    "ステュアート",
    "スミス",
    "",
    "リカード",
    "",
    "ミル",
    "",
    "マーシャル",
    "ケインズ",
    "",
    "シュムペーター",
    "論理",
    "的",
    "視座",
    "究明",
    "試み",
    "",
    "東",
    "東南アジア",
    "問題",
    "点",
    "その",
    "解決",
    "道",
    "探る",
    "力作"
  ],
  "title": "国際経済・貿易の変遷と将来への展望"
}