{
  "biblio_authors": "吉田 和男",
  "biblio_location": "相1F一般300",
  "biblio_publisher": "有斐閣",
  "biblio_year_published": "2002.12",
  "description": "IT革命は、経済の主役を「資本」から「情報」へと移行させる。「資本主義経済」から「知識経済」への移行が議論されているのは、まさにこの変革を意味している。そして、その中心的役者であった「企業」に代わるものは「ネット」である。すなわち、企業社会がネット社会へと変身する。",
  "identifier": "4641161631",
  "keywords": [],
  "lexemes": [
    "IT",
    "革命",
    "経済",
    "主役",
    "資本",
    "情報",
    "移行",
    "さ",
    "せる",
    "資本",
    "主義",
    "経済",
    "知識",
    "経済",
    "移行",
    "議論",
    "さ",
    "れ",
    "いる",
    "の",
    "まさに",
    "この",
    "変革",
    "意味",
    "し",
    "いる",
    "そして",
    "その",
    "中心",
    "的",
    "役者",
    "で",
    "あっ",
    "た",
    "企業",
    "代わる",
    "もの",
    "ネット",
    "で",
    "ある",
    "すなわち",
    "企業",
    "社会",
    "ネット",
    "社会",
    "変身",
    "する"
  ],
  "title": "IT経済学入門"
}