{
  "biblio_authors": "伊藤 邦雄",
  "biblio_location": "相1F一般300",
  "biblio_publisher": "日本経済新聞社",
  "biblio_year_published": "2000.3",
  "description": "ソニー、アスクル、デル、アマゾン...強烈な個性と競争優位を築いた企業に、資本も人も集中する。革新的な「ビジネスモデル」を考え抜き、強い企業ブランドを確立せよ。株主、顧客、従業員を束ねる、新世紀の経営モデル。",
  "identifier": "4532148189",
  "keywords": [],
  "lexemes": [
    "ソニー",
    "アスクル",
    "デル",
    "アマゾン",
    "強烈",
    "な",
    "個性",
    "競争",
    "優位",
    "築い",
    "た",
    "企業",
    "資本",
    "人",
    "集中",
    "する",
    "革新",
    "的",
    "な",
    "ビジネス",
    "モデル",
    "考え抜き",
    "強い",
    "企業",
    "ブランド",
    "確立",
    "せよ",
    "株主",
    "顧客",
    "従業",
    "員",
    "束ねる",
    "新",
    "世紀",
    "経営",
    "モデル"
  ],
  "title": "コーポレートブランド経営"
}