{
  "biblio_authors": "横山 宏章",
  "biblio_location": "相1F一般300",
  "biblio_publisher": "集英社",
  "biblio_year_published": "2005.8",
  "description": "近年、中国では反日感情が高まり、日本でも反中感情が芽生えている。経済的にはますます相互依存が深まっている両国で、いまなぜこうした現象が起きているのだろうか?近代以降の日中関係には、靖国神社参拝や尖閣諸島、歴史教科書といった個別の問題だけでは説明することのできない、長い歴史のなかで形成された複雑な国民感情が横たわっている。現代に影響を与え続ける日中の歴史をひもときながら、不毛な感情的対立を超え、東アジアの両国が共に発展しうる道程をさぐる。",
  "identifier": "4087203069",
  "keywords": [],
  "lexemes": [
    "近年",
    "中国",
    "反日",
    "感情",
    "高まり",
    "日本",
    "反",
    "中",
    "感情",
    "芽生え",
    "いる",
    "経済",
    "的",
    "ますます",
    "相互",
    "依存",
    "深まっ",
    "いる",
    "両国",
    "いま",
    "なぜ",
    "こうした",
    "現象",
    "起き",
    "いる",
    "の",
    "だろ",
    "う",
    "近代",
    "以降",
    "日",
    "中",
    "関係",
    "靖国神社",
    "参拝",
    "尖閣諸島",
    "歴史",
    "教科書",
    "個別",
    "問題",
    "で",
    "説明",
    "する",
    "こと",
    "でき",
    "ない",
    "長い",
    "歴史",
    "なか",
    "形成",
    "さ",
    "れ",
    "た",
    "複雑",
    "な",
    "国民",
    "感情",
    "横たわっ",
    "いる",
    "現代",
    "影響",
    "与え",
    "続ける",
    "日",
    "中",
    "歴史",
    "ひもとき",
    "不毛",
    "な",
    "感情",
    "的",
    "対立",
    "超え",
    "東アジア",
    "両国",
    "共に",
    "発展",
    "し",
    "うる",
    "道程",
    "さぐる"
  ],
  "title": "反日と反中"
}