{
  "biblio_authors": "新崎 盛暉",
  "biblio_location": "相1F一般300",
  "biblio_publisher": "高文研",
  "biblio_year_published": "1997.8",
  "description": "沖縄を知れば、「日本」が見えてくる!沖縄はこれまで何を体験し、何を見てきたのか!?今も残る沖縄戦の跡をたどり、広大な軍事基地をあるき、自立を求めて揺れ動く「今日の沖縄」の素顔を伝える。",
  "identifier": "4874981917",
  "keywords": [],
  "lexemes": [
    "沖縄",
    "知れ",
    "日本",
    "見え",
    "くる",
    "沖縄",
    "これ",
    "何",
    "体験",
    "し",
    "何",
    "見",
    "き",
    "た",
    "の",
    "今",
    "残る",
    "沖縄",
    "戦",
    "跡",
    "たどり",
    "広大",
    "な",
    "軍事",
    "基地",
    "あるき",
    "自立",
    "求め",
    "揺れ動く",
    "今日",
    "沖縄",
    "素顔",
    "伝える"
  ],
  "title": "観光コースでない沖縄"
}