{
  "biblio_authors": "LazarusArnold A",
  "biblio_location": "相1F一般300",
  "biblio_publisher": "ダイヤモンド社",
  "biblio_year_published": "2003.11",
  "description": "「なんでもわかり合える夫婦」なんて、ウソだ!ベテラン心理学者が教えてくれる「本当のこと」とは?「理想の結婚」イメージに縛られていませんか?これから結婚する人には、幸せな結婚生活を送るための準備として、すでに結婚していて「これでよかったのかな?」と思っている人には、二人の関係を見直しより満ち足りたものとするために、そして離婚経験のある人には、次に失敗しないために、必ず役に立つケースとヒントがあります。",
  "identifier": "4478710570",
  "keywords": [],
  "lexemes": [
    "なん",
    "わかり",
    "合える",
    "夫婦",
    "ウソ",
    "だ",
    "ベテラン",
    "心理",
    "学者",
    "教え",
    "くれる",
    "本当",
    "こと",
    "理想",
    "結婚",
    "イメージ",
    "縛ら",
    "れ",
    "い",
    "ませ",
    "ん",
    "これから",
    "結婚",
    "する",
    "人",
    "幸せ",
    "な",
    "結婚",
    "生活",
    "送る",
    "ため",
    "準備",
    "すでに",
    "結婚",
    "し",
    "い",
    "これ",
    "で",
    "よかっ",
    "た",
    "の",
    "思っ",
    "いる",
    "人",
    "二",
    "人",
    "関係",
    "見直し",
    "満ち足り",
    "た",
    "もの",
    "する",
    "ため",
    "そして",
    "離婚",
    "経験",
    "ある",
    "人",
    "次に",
    "失敗",
    "し",
    "ない",
    "ため",
    "必ず",
    "役に立つ",
    "ケース",
    "ヒント",
    "あり",
    "ます"
  ],
  "title": "秘密があるほうが、男と女はうまくいく"
}