{
  "biblio_authors": "東京経済大学国際経済グループ",
  "biblio_location": "相1F一般300",
  "biblio_publisher": "有斐閣",
  "biblio_year_published": "2013.4",
  "description": "身近なニュースや話題から世界経済に親しみ、その仕組みを解き明かす学問の世界へ案内します。第3版では「資格とエネルギー」や「BRICs」の章を設け、内容・データともに最新動向を盛り込みました。",
  "identifier": "9784641184121",
  "keywords": [],
  "lexemes": [
    "身近",
    "な",
    "ニュース",
    "話題",
    "世界",
    "経済",
    "親しみ",
    "その",
    "仕組み",
    "解き明かす",
    "学問",
    "世界",
    "案内",
    "し",
    "ます",
    "第",
    "3",
    "版",
    "で",
    "資格",
    "エネルギー",
    "BRICs",
    "章",
    "設け",
    "内容",
    "データ",
    "とも",
    "最新",
    "動向",
    "盛り込み",
    "まし",
    "た"
  ],
  "title": "私たちの国際経済"
}