{
  "biblio_authors": "河野 勝",
  "biblio_location": "相1F一般300",
  "biblio_publisher": "勁草書房",
  "biblio_year_published": "2009.9",
  "description": "グローバル化する世界のなかで、ヒト、組織、国家の期待が実現する社会の可能性を問う、新しい政治経済学の挑戦。",
  "identifier": "9784326301812",
  "keywords": [],
  "lexemes": [
    "グローバル",
    "化",
    "する",
    "世界",
    "なか",
    "ヒト",
    "組織",
    "国家",
    "期待",
    "実現",
    "する",
    "社会",
    "可能",
    "性",
    "問う",
    "新しい",
    "政治",
    "経済",
    "学",
    "挑戦"
  ],
  "title": "期待,制度,グローバル社会"
}