{
  "biblio_authors": "池田 謙一",
  "biblio_location": "相1F一般300",
  "biblio_publisher": "勁草書房",
  "biblio_year_published": "2016.4",
  "description": "日本人は競争を追求するのか。日本は世界に開かれているのか閉じこもっているのか。グローバル化の中で世界の人々の考え方は似通ってきているのだろうか。",
  "identifier": "9784326251162",
  "keywords": [],
  "lexemes": [
    "日本人",
    "競争",
    "追求",
    "する",
    "の",
    "日本",
    "世界",
    "開か",
    "れ",
    "いる",
    "の",
    "閉じこもっ",
    "いる",
    "の",
    "グローバル",
    "化",
    "中",
    "世界",
    "人々",
    "考え方",
    "似通っ",
    "き",
    "いる",
    "の",
    "だろ",
    "う"
  ],
  "title": "日本人の考え方世界の人の考え方"
}