{
  "biblio_authors": "土田 陽介",
  "biblio_location": "相1F一般300",
  "biblio_publisher": "筑摩書房",
  "biblio_year_published": "2019.10",
  "description": "財政赤字の拡大、金融緩和政策の横行......通貨の信認が失われた先に何があるのか? その絵姿を「ドル化」という視点から描き出す。",
  "identifier": "9784480072627",
  "keywords": [],
  "lexemes": [
    "財政",
    "赤字",
    "拡大",
    "金融",
    "緩和",
    "政策",
    "横行",
    "通貨",
    "信認",
    "失わ",
    "れ",
    "た",
    "先",
    "何",
    "ある",
    "の",
    "その",
    "絵姿",
    "ドル",
    "化",
    "視点",
    "描き出す"
  ],
  "title": "ドル化とは何か"
}