{
  "biblio_authors": "荒井 悠介",
  "biblio_location": "相1F一般300",
  "biblio_publisher": "新潮社",
  "biblio_year_published": "2009.10",
  "description": "真っ黒な肌、奇抜なメイクにド派手なファッション。ストリートにたむろし、クラブでパーティー―。日本を席巻し始めたギャル文化の象徴「イベサー」を、かつて集団のトップを務めた男がフィールドワーク。数百人のギャルの肉声から、現代の「未開の部族」の内面に迫る。「やっぱり礼儀と学歴は大事」「いかに早く遊んで落ち着くか」など、その奔放なセックス観から意外に保守的な未来像まで、彼らの素顔を大解剖。",
  "identifier": "9784106103346",
  "keywords": [],
  "lexemes": [
    "真っ黒",
    "な",
    "肌",
    "奇抜",
    "な",
    "メイク",
    "ド",
    "派手",
    "な",
    "ファッション",
    "ストリート",
    "たむろ",
    "し",
    "クラブ",
    "パーティー",
    "日本",
    "席巻",
    "し",
    "始め",
    "た",
    "ギャル",
    "文化",
    "象徴",
    "イベサー",
    "かつて",
    "集団",
    "トップ",
    "務め",
    "た",
    "男",
    "フィールドワーク",
    "数",
    "百",
    "人",
    "ギャル",
    "肉声",
    "現代",
    "未開",
    "部族",
    "内面",
    "迫る",
    "やっぱり",
    "礼儀",
    "学歴",
    "大事",
    "いかに",
    "早く",
    "遊ん",
    "落ち着く",
    "その",
    "奔放",
    "な",
    "セックス",
    "観",
    "意外",
    "保守",
    "的",
    "な",
    "未来",
    "像",
    "彼ら",
    "素顔",
    "大",
    "解剖"
  ],
  "title": "ギャルとギャル男の文化人類学"
}