{
  "biblio_authors": "山田 鋭夫",
  "biblio_location": "相1F一般300",
  "biblio_publisher": "藤原書店",
  "biblio_year_published": "2008.9",
  "description": "資本主義は、政治・労働・教育・社会保障・文化...といった「社会的なもの」と「資本的なもの」との複合的総体である。つまり、各地域で極めて多様である。このような“複合体”としての資本主義を、国別・類型別に比較することで、新しい社会=歴史認識を汲みとり、現代社会の動きを俯瞰することができる。",
  "identifier": "9784894346499",
  "keywords": [],
  "lexemes": [
    "資本",
    "主義",
    "政治",
    "労働",
    "教育",
    "社会",
    "保障",
    "文化",
    "社会",
    "的",
    "な",
    "もの",
    "資本",
    "的",
    "な",
    "もの",
    "複合",
    "的",
    "総体",
    "で",
    "ある",
    "つまり",
    "各",
    "地域",
    "極めて",
    "多様",
    "で",
    "ある",
    "この",
    "よう",
    "な",
    "複合",
    "体",
    "資本",
    "主義",
    "国",
    "別",
    "類型",
    "別",
    "比較",
    "する",
    "こと",
    "で",
    "新しい",
    "社会",
    "歴史",
    "認識",
    "汲み",
    "とり",
    "現代",
    "社会",
    "動き",
    "俯瞰",
    "する",
    "こと",
    "できる"
  ],
  "title": "さまざまな資本主義"
}