{
  "biblio_authors": "長山 靖生",
  "biblio_location": "相1F一般300",
  "biblio_publisher": "新潮社",
  "biblio_year_published": "2007.3",
  "description": "かつて先人たちは「老い」をいかに受け入れ、余生をどのように過ごしてきたのか―?経験と知恵を伝え、尊厳を保っていた昔日の隠居制から、年金制度崩壊や熟年離婚激増など不安多き現代社会まで...時代ごとに、高齢者の姿と余生のあり方の変遷に光を当て、考察した画期的な一冊。先人たちの生き様に、未来のあなたの姿が見えてくる...。",
  "identifier": "9784106035777",
  "keywords": [],
  "lexemes": [
    "かつて",
    "先人",
    "たち",
    "老い",
    "いかに",
    "受け入れ",
    "余生",
    "どの",
    "よう",
    "過ごし",
    "き",
    "た",
    "の",
    "経験",
    "知恵",
    "伝え",
    "尊厳",
    "保っ",
    "い",
    "た",
    "昔日",
    "隠居",
    "制",
    "年金",
    "制度",
    "崩壊",
    "熟年",
    "離婚",
    "激増",
    "不安",
    "多き",
    "現代",
    "社会",
    "時代",
    "ごと",
    "高齢",
    "者",
    "姿",
    "余生",
    "あり方",
    "変遷",
    "光",
    "当て",
    "考察",
    "し",
    "た",
    "画期的",
    "な",
    "一",
    "冊",
    "先人",
    "たち",
    "生き",
    "様",
    "未来",
    "あなた",
    "姿",
    "見え",
    "くる"
  ],
  "title": "日本人の老後"
}