{
  "biblio_authors": "藁谷 哲也",
  "biblio_location": "相1F一般300",
  "biblio_publisher": "文眞堂",
  "biblio_year_published": "2019.9",
  "description": "長年にわたる内戦・混乱から抜け出し、急速な成長と発展の軌道に乗り始めたカンボジア王国の実情とそのプロセスをわかりやすく紹介。",
  "identifier": "9784830950445",
  "keywords": [],
  "lexemes": [
    "長年",
    "内戦",
    "混乱",
    "抜け出し",
    "急速",
    "な",
    "成長",
    "発展",
    "軌道",
    "乗り",
    "始め",
    "た",
    "カンボジア",
    "王国",
    "実情",
    "その",
    "プロセス",
    "わかり",
    "やすく",
    "紹介"
  ],
  "title": "カンボジア研究"
}