{
  "biblio_authors": "林 京子",
  "biblio_location": "相1F一般300",
  "biblio_publisher": "岩波書店",
  "biblio_year_published": "2011.7",
  "description": "学徒動員先の長崎三菱兵器工場での被爆を描いた小説「祭りの場」以来、人が被爆体験を抱えながら生きることの意味を、深く静かに問い続けてきた作家、林京子。戦時下の上海で過ごした幼少時代、引揚げ後の被爆から、福島原発事故によって再び眼前に「核」が突きつけられた2011年3月11日まで―その生涯を、作品と重ねて語る。",
  "identifier": "9784002708133",
  "keywords": [],
  "lexemes": [
    "学徒",
    "動員",
    "先",
    "長崎",
    "三菱",
    "兵器",
    "工場",
    "被爆",
    "描い",
    "た",
    "小説",
    "祭り",
    "場",
    "以来",
    "人",
    "被爆",
    "体験",
    "抱え",
    "生きる",
    "こと",
    "意味",
    "深く",
    "静か",
    "問い",
    "続け",
    "き",
    "た",
    "作家",
    "林",
    "京子",
    "戦時",
    "下",
    "上海",
    "過ごし",
    "た",
    "幼少",
    "時代",
    "引",
    "揚げ",
    "後",
    "被爆",
    "福島",
    "原発",
    "事故",
    "再び",
    "眼前",
    "核",
    "突きつけ",
    "られ",
    "た",
    "2011",
    "年",
    "3",
    "月",
    "11",
    "日",
    "その",
    "生涯",
    "作品",
    "重ね",
    "語る"
  ],
  "title": "被爆を生きて"
}