{
  "biblio_authors": "鎌田 薫",
  "biblio_location": "相1F一般300",
  "biblio_publisher": "日本評論社",
  "biblio_year_published": "2010.4",
  "description": "実体法と訴訟法を有機的に関連づけ、理論と実務の双方から検証する必携のテキスト。民法・民事訴訟法の研究者と司法研修所教官、裁判官の共同作業により、「設問」「解説」「問題の背景」の構成で、より深く理解できるよう工夫。新たに、読者の便宜のために、「民事訴訟手続と設問との関連一覧」を収録。",
  "identifier": "9784535516939",
  "keywords": [],
  "lexemes": [
    "実体",
    "法",
    "訴訟",
    "法",
    "有機",
    "的",
    "関連づけ",
    "理論",
    "実務",
    "双方",
    "検証",
    "する",
    "必携",
    "テキスト",
    "民法",
    "民事",
    "訴訟",
    "法",
    "研究",
    "者",
    "司法研修所",
    "教官",
    "裁判官",
    "共同",
    "作業",
    "設問",
    "解説",
    "問題",
    "背景",
    "構成",
    "より",
    "深く",
    "理解",
    "できる",
    "よう",
    "工夫",
    "新た",
    "読者",
    "便宜",
    "ため",
    "民事",
    "訴訟",
    "手続",
    "設問",
    "関連",
    "一覧",
    "収録"
  ],
  "title": "民事法 1"
}