{
  "biblio_authors": "松本 礼二",
  "biblio_location": "相1F一般300",
  "biblio_publisher": "みすず書房",
  "biblio_year_published": "2011.12",
  "description": "21世紀にToquevilleは何を語りかけてくるか。『アメリカのデモクラシー』『アンシャン・レジームと革命』読解や研究史の分析から、生きた全体像を提示する。",
  "identifier": "9784622076728",
  "keywords": [],
  "lexemes": [
    "21",
    "世紀",
    "Toqueville",
    "何",
    "語りかけ",
    "くる",
    "アメリカ",
    "デモクラシー",
    "アン",
    "シャン",
    "レジーム",
    "革命",
    "読解",
    "研究",
    "史",
    "分析",
    "生き",
    "た",
    "全体",
    "像",
    "提示",
    "する"
  ],
  "title": "トクヴィルで考える"
}