{
  "biblio_authors": "Oppenheimer Andres 1951-",
  "biblio_location": "相1F一般300",
  "biblio_publisher": "時事通信出版局",
  "biblio_year_published": "2011.7",
  "description": "ラテンアメリカは成長し続けるのか、それとも台頭するアジアに圧倒され凋落の道をたどるのか!?マイアミ・ヘラルド紙の名物コラムニストでピューリッツアー賞受賞ジャーナリストが米州の諸問題について複眼的な視点で大胆に切り込んでいく。",
  "identifier": "9784788711631",
  "keywords": [],
  "lexemes": [
    "ラテンアメリカ",
    "成長",
    "し",
    "続ける",
    "の",
    "それとも",
    "台頭",
    "する",
    "アジア",
    "圧倒",
    "さ",
    "れ",
    "凋落",
    "道",
    "たどる",
    "の",
    "マイアミ・ヘラルド",
    "紙",
    "名物",
    "コラムニスト",
    "ピューリッツアー",
    "賞",
    "受賞",
    "ジャーナリスト",
    "米州",
    "諸",
    "問題",
    "複眼",
    "的",
    "な",
    "視点",
    "大胆",
    "切り込ん",
    "いく"
  ],
  "title": "米州救出"
}