{
  "biblio_authors": "浦野 研",
  "biblio_location": "相1F一般300",
  "biblio_publisher": "研究社",
  "biblio_year_published": "2016.8",
  "description": "英語教育研究に興味のある大学生・院生や英語教員のための入門書。研究の一連のプロセスについて、具体例とともに分かりやすく解説。",
  "identifier": "9784327421977",
  "keywords": [],
  "lexemes": [
    "英語",
    "教育",
    "研究",
    "興味",
    "ある",
    "大学生",
    "院生",
    "英語",
    "教員",
    "ため",
    "入門",
    "書",
    "研究",
    "一連",
    "プロセス",
    "具体",
    "例",
    "分かり",
    "やすく",
    "解説"
  ],
  "title": "はじめての英語教育研究"
}