{
  "biblio_authors": "手嶋 教之",
  "biblio_location": "相1F一般300",
  "biblio_publisher": "コロナ社",
  "biblio_year_published": "2009.2",
  "description": "This book discusses the rehabilitation devices that assist the elderly and physically disabled, such as mobile equipment, prosthesis, and equipment for the visually impaired. It explains the functions of these devices and how to choose and use them. It also describes universal designs and impediment removals.",
  "identifier": "9784339045239",
  "keywords": [],
  "lexemes": [
    "This",
    "book",
    "discusses",
    "the",
    "rehabilitation",
    "devices",
    "that",
    "assist",
    "the",
    "elderly",
    "and",
    "physically",
    "disabled",
    "",
    "such",
    "as",
    "mobile",
    "equipment",
    "",
    "prosthesis",
    "",
    "and",
    "equipment",
    "for",
    "the",
    "visually",
    "impaired",
    "It",
    "explains",
    "the",
    "functions",
    "of",
    "these",
    "devices",
    "and",
    "how",
    "to",
    "choose",
    "and",
    "use",
    "them",
    "It",
    "also",
    "describes",
    "universal",
    "designs",
    "and",
    "impediment",
    "removals"
  ],
  "title": "基礎福祉工学"
}