{
  "biblio_authors": "清水 美和",
  "biblio_location": "相1F一般300",
  "biblio_publisher": "筑摩書房",
  "biblio_year_published": "2009.9",
  "description": "建国60周年をむかえた人民共和国に、搾取を否定した「赤い」理念はもはやない。「人民」不在で進められる改革・開放が、陰惨な矛盾を社会にもたらし、国家の基盤が激しく揺らいでいる。その制御をもくろむ共産党指導部は、軍備を増強してナショナリズムを強め、国家の凝集力を高めようとするが...。毒ギョーザ事件、新疆動乱、尖閣諸島、米国との接近。日本人の想像も及ばない大国で、いま、何が起きているのか。中国各地を精力的に取材しつづける実力派ジャーナリストが、共産党政権の内部事情を精確に分析し、現代史的な視点から「巨龍」の生態を描く。",
  "identifier": "9784480065063",
  "keywords": [],
  "lexemes": [
    "建国",
    "60",
    "周年",
    "むかえ",
    "た",
    "人民",
    "共和",
    "国",
    "搾取",
    "否定",
    "し",
    "た",
    "赤い",
    "理念",
    "もはや",
    "ない",
    "人民",
    "不在",
    "進め",
    "られる",
    "改革",
    "開放",
    "陰惨",
    "な",
    "矛盾",
    "社会",
    "もたらし",
    "国家",
    "基盤",
    "激しく",
    "揺らい",
    "いる",
    "その",
    "制御",
    "もくろむ",
    "共産党",
    "指導",
    "部",
    "軍備",
    "増強",
    "し",
    "ナショナリズム",
    "強め",
    "国家",
    "凝集",
    "力",
    "高めよ",
    "う",
    "する",
    "毒",
    "ギョーザ",
    "事件",
    "新",
    "疆",
    "動乱",
    "尖閣諸島",
    "米国",
    "接近",
    "日本人",
    "想像",
    "及ば",
    "ない",
    "大国",
    "いま",
    "何",
    "起き",
    "いる",
    "の",
    "中国",
    "各地",
    "精力",
    "的",
    "取材",
    "し",
    "つづける",
    "実力",
    "派",
    "ジャーナリスト",
    "共産党",
    "政権",
    "内部",
    "事情",
    "精確",
    "分析",
    "し",
    "現代",
    "史",
    "的",
    "な",
    "視点",
    "巨龍",
    "生態",
    "描く"
  ],
  "title": "「中国問題」の核心"
}