{
  "biblio_authors": "実川 真由",
  "biblio_location": "相1F一般300",
  "biblio_publisher": "文藝春秋",
  "biblio_year_published": "2007.9",
  "description": "日本の中高一貫進学校に通う普通の女子高生が世界一の教育を体験した。塾もない。偏差値もない。なのに世界一。なぜ?フィンランドの公立高校に一年間留学した娘とその母親の両方の立場から書かれた本です。留学の準備から、在籍高校との調整、帰国後の進学・就職まで親子が知りたい情報が満載。",
  "identifier": "9784163694504",
  "keywords": [],
  "lexemes": [
    "日本",
    "中高",
    "一貫",
    "進学校",
    "通う",
    "普通",
    "女子高",
    "生",
    "世界一",
    "教育",
    "体験",
    "し",
    "た",
    "塾",
    "ない",
    "偏差",
    "値",
    "ない",
    "なのに",
    "世界一",
    "なぜ",
    "フィンランド",
    "公立",
    "高校",
    "一",
    "年間",
    "留学",
    "し",
    "た",
    "娘",
    "その",
    "母親",
    "両方",
    "立場",
    "書か",
    "れ",
    "た",
    "本",
    "です",
    "留学",
    "準備",
    "在籍",
    "高校",
    "調整",
    "帰国",
    "後",
    "進学",
    "就職",
    "親子",
    "知り",
    "たい",
    "情報",
    "満載"
  ],
  "title": "受けてみたフィンランドの教育"
}