{
  "biblio_authors": "菅原 晃",
  "biblio_location": "相1F一般300",
  "biblio_publisher": "KADOKAWA",
  "biblio_year_published": "2014.10",
  "description": "現代社会も世界史も、経済学から読みとけば、今まで謎だったことが氷解します。本書は見開き半分を図解で構成。図解の中で経済学者たちが熱く議論を戦わせます。その中身に触れれば、経済と世の中を読みとくためのブレない「モノサシ」が自然と身につきます。",
  "identifier": "9784046005915",
  "keywords": [],
  "lexemes": [
    "現代",
    "社会",
    "世界",
    "史",
    "経済",
    "学",
    "読み",
    "とけ",
    "今",
    "謎",
    "だっ",
    "た",
    "こと",
    "氷解",
    "し",
    "ます",
    "本書",
    "見開き",
    "半分",
    "図解",
    "構成",
    "図解",
    "中",
    "経済",
    "学者",
    "たち",
    "熱く",
    "議論",
    "戦わ",
    "せ",
    "ます",
    "その",
    "中身",
    "触れれ",
    "経済",
    "世の中",
    "読み",
    "とく",
    "ため",
    "ブレ",
    "ない",
    "モノサシ",
    "自然",
    "身",
    "つき",
    "ます"
  ],
  "title": "図解使えるマクロ経済学"
}