{
  "biblio_authors": "田嶋 一",
  "biblio_location": "相1F一般300",
  "biblio_publisher": "有斐閣",
  "biblio_year_published": "2016.12",
  "description": "「教育とは何か」という大きな問題に、広く深く取り組めるように工夫しました。経験と思考の間を行き来しながら、教育の世界に迫っていくために、具体的な素材を組み込み、問いかけを仕組んでおきました。答えは共に探究しましょう。",
  "identifier": "9784641220812",
  "keywords": [],
  "lexemes": [
    "教育",
    "何",
    "大きな",
    "問題",
    "広く",
    "深く",
    "取り組める",
    "よう",
    "工夫",
    "し",
    "まし",
    "た",
    "経験",
    "思考",
    "間",
    "行き来",
    "し",
    "教育",
    "世界",
    "迫っ",
    "いく",
    "ため",
    "具体",
    "的",
    "な",
    "素材",
    "組み込み",
    "問いかけ",
    "仕組ん",
    "おき",
    "まし",
    "た",
    "答え",
    "共に",
    "探究",
    "し",
    "ましょ",
    "う"
  ],
  "title": "やさしい教育原理"
}