{
  "biblio_authors": "Va?sse Maurice",
  "biblio_location": "相1F一般300",
  "biblio_publisher": "慶應義塾大学出版会",
  "biblio_year_published": "2018.8",
  "description": "世界的権威による、多くの国で翻訳されているロングセラー。外交・軍事のみならず、多彩な視点からの背景を解説。大国に偏らず、世界の各地域の相互の関係の変化を明快に描く。第二次世界大戦後、世界は二極化を経て、なぜ現在のような混迷の時代になったのか?国際政治史の世界的権威が、激動の戦後史を外交や軍事だけでなく、経済・社会・文化の広い視点からダイナミックに描き出す。日本や中国を含む東アジア地域についての記述を大幅に追加した最新版の翻訳。",
  "identifier": "9784766425345",
  "keywords": [],
  "lexemes": [
    "世界",
    "的",
    "権威",
    "多く",
    "国",
    "翻訳",
    "さ",
    "れ",
    "いる",
    "ロングセラー",
    "外交",
    "軍事",
    "なら",
    "ず",
    "多彩",
    "な",
    "視点",
    "背景",
    "解説",
    "大国",
    "偏ら",
    "ず",
    "世界",
    "各",
    "地域",
    "相互",
    "関係",
    "変化",
    "明快",
    "描く",
    "第",
    "二",
    "次",
    "世界",
    "大戦",
    "後",
    "世界",
    "二",
    "極",
    "化",
    "経",
    "なぜ",
    "現在",
    "よう",
    "な",
    "混迷",
    "時代",
    "なっ",
    "た",
    "の",
    "国際",
    "政治",
    "史",
    "世界",
    "的",
    "権威",
    "激動",
    "戦後",
    "史",
    "外交",
    "軍事",
    "で",
    "なく",
    "経済",
    "社会",
    "文化",
    "広い",
    "視点",
    "ダイナミック",
    "描き出す",
    "日本",
    "中国",
    "含む",
    "東アジア",
    "地域",
    "記述",
    "大幅",
    "追加",
    "し",
    "た",
    "最新",
    "版",
    "翻訳"
  ],
  "title": "戦後国際関係史"
}