{
  "biblio_authors": "Piketty Thomas 1971-",
  "biblio_location": "相1F一般300",
  "biblio_publisher": "Belknap Press of Harvard University Press",
  "biblio_year_published": "2014",
  "description": "The main driver of inequality--returns on capital that exceed the rate of economic growth--is again threatening to generate extreme discontent and undermine democratic values. Thomas Piketty's findings in this ambitious, original, rigorous work will transform debate and set the agenda for the next generation of thought about wealth and inequality.",
  "identifier": "9780674430006",
  "keywords": [],
  "lexemes": [
    "The",
    "main",
    "driver",
    "of",
    "inequality",
    "returns",
    "on",
    "capital",
    "that",
    "exceed",
    "the",
    "rate",
    "of",
    "economic",
    "growth",
    "is",
    "again",
    "threatening",
    "to",
    "generate",
    "extreme",
    "discontent",
    "and",
    "undermine",
    "democratic",
    "values",
    "Thomas",
    "Piketty",
    "s",
    "findings",
    "in",
    "this",
    "ambitious",
    "",
    "original",
    "",
    "rigorous",
    "work",
    "will",
    "transform",
    "debate",
    "and",
    "set",
    "the",
    "agenda",
    "for",
    "the",
    "next",
    "generation",
    "of",
    "thought",
    "about",
    "wealth",
    "and",
    "inequality"
  ],
  "title": "Capital in the Twenty-First Century"
}