{
  "biblio_authors": "濱口 桂一郎",
  "biblio_location": "相1F一般300",
  "biblio_publisher": "日本経済新聞出版社",
  "biblio_year_published": "2011.9",
  "description": "働く現実と法の関係をトータルに理解する。雇用管理、人事・賃金制度、労使関係など日本の特質と問題点を丁寧に解説した画期的入門書。",
  "identifier": "9784532112486",
  "keywords": [],
  "lexemes": [
    "働く",
    "現実",
    "法",
    "関係",
    "トータル",
    "理解",
    "する",
    "雇用",
    "管理",
    "人事",
    "賃金",
    "制度",
    "労使",
    "関係",
    "日本",
    "特質",
    "問題",
    "点",
    "丁寧",
    "解説",
    "し",
    "た",
    "画期的",
    "入門",
    "書"
  ],
  "title": "日本の雇用と労働法"
}