{
  "biblio_authors": "今野 浩一郎",
  "biblio_location": "相1F一般300",
  "biblio_publisher": "日経BP日本経済新聞出版本部",
  "biblio_year_published": "2020.5",
  "description": "同一労働同一賃金、ダイバーシティ、ジョブ型雇用――。人事管理のベストテキストを環境変化に即応して全面改訂。データも刷新。",
  "identifier": "9784532135027",
  "keywords": [],
  "lexemes": [
    "同",
    "一",
    "労働",
    "同",
    "一",
    "賃金",
    "ダイバー",
    "シティ",
    "ジョブ",
    "型",
    "雇用",
    "人事",
    "管理",
    "ベスト",
    "テキスト",
    "環境",
    "変化",
    "即応",
    "し",
    "全面",
    "改訂",
    "データ",
    "刷新"
  ],
  "title": "マネジメント・テキスト人事管理入門"
}