{
  "biblio_authors": "Schneier Bruce 1963-",
  "biblio_location": "相1F一般300",
  "biblio_publisher": "日経BP社",
  "biblio_year_published": "2007.2",
  "description": "テロ、ハイジャック、カード犯罪、ネット犯罪―現代社会にひそむ脅威への賢い防御とは。『暗号の秘密とウソ』の著者、待望の最新刊。",
  "identifier": "9784822283100",
  "keywords": [],
  "lexemes": [
    "テロ",
    "ハイジャック",
    "カード",
    "犯罪",
    "ネット",
    "犯罪",
    "現代",
    "社会",
    "ひそむ",
    "脅威",
    "賢い",
    "防御",
    "暗号",
    "秘密",
    "ウソ",
    "著者",
    "待望",
    "最新",
    "刊"
  ],
  "title": "セキュリティはなぜやぶられたのか"
}