{
  "biblio_authors": "月村 太郎",
  "biblio_location": "相1F一般300",
  "biblio_publisher": "岩波書店",
  "biblio_year_published": "2013.6",
  "description": "世界各地で続発している民族紛争。どのように発生、激化し、そして終結へと向かうのか。クロアチアとボスニア、コソヴォ、ルワンダ、スリランカなど六つの紛争の経緯を詳しく紹介し、軍事介入やジェノサイドの実態などについて考察する。さらに民族紛争に関する研究の論点を整理し、紛争予防や平和構築の可能性を検討する。",
  "identifier": "9784004314318",
  "keywords": [],
  "lexemes": [
    "世界",
    "各地",
    "続発",
    "し",
    "いる",
    "民族",
    "紛争",
    "どの",
    "よう",
    "発生",
    "激化",
    "し",
    "そして",
    "終結",
    "向かう",
    "の",
    "クロアチア",
    "ボスニア",
    "コソヴォ",
    "ルワンダ",
    "スリランカ",
    "六つ",
    "紛争",
    "経緯",
    "詳しく",
    "紹介",
    "し",
    "軍事",
    "介入",
    "ジェノサイド",
    "実態",
    "考察",
    "する",
    "さらに",
    "民族",
    "紛争",
    "研究",
    "論点",
    "整理",
    "し",
    "紛争",
    "予防",
    "平和",
    "構築",
    "可能",
    "性",
    "検討",
    "する"
  ],
  "title": "民族紛争"
}