{
  "biblio_authors": "河合 克義",
  "biblio_location": "相1F一般300",
  "biblio_publisher": "光文社",
  "biblio_year_published": "2015.7",
  "description": "“大切なもの”が欠落する日本の社会保障・福祉制度“高齢者3000万人時代”に必要な視点そして問題解決へのシナリオ。",
  "identifier": "9784334038700",
  "keywords": [],
  "lexemes": [
    "大切",
    "な",
    "もの",
    "欠落",
    "する",
    "日本",
    "社会",
    "保障",
    "福祉",
    "制度",
    "高齢",
    "者",
    "3000",
    "万",
    "人",
    "時代",
    "必要",
    "な",
    "視点",
    "そして",
    "問題",
    "解決",
    "シナリオ"
  ],
  "title": "老人に冷たい国・日本"
}