{
  "biblio_authors": "原田 晃樹",
  "biblio_location": "相1F一般300",
  "biblio_publisher": "勁草書房",
  "biblio_year_published": "2010.4",
  "description": "行政の下請け化と商業化。2つの危機に直面するNPOが進むべき第3の道とは?社会的企業論やイギリスの協働政策から学び、自治体との契約手法にまで切り込む。",
  "identifier": "9784326602285",
  "keywords": [],
  "lexemes": [
    "行政",
    "下請け",
    "化",
    "商業",
    "化",
    "2",
    "つ",
    "危機",
    "直面",
    "する",
    "NPO",
    "進む",
    "べき",
    "第",
    "3",
    "道",
    "社会",
    "的",
    "企業",
    "論",
    "イギリス",
    "協",
    "働",
    "政策",
    "学び",
    "自治体",
    "契約",
    "手法",
    "切り込む"
  ],
  "title": "NPO再構築への道"
}